ripgrep_rs/__init__.py
ripgrep_rs/__init__.pyi
ripgrep_rs/py.typed
ripgrep_rs/ripgrep_rs.cpython-312-darwin.so
ripgrep_rs-0.3.15.dist-info/METADATA
ripgrep_rs-0.3.15.dist-info/WHEEL
ripgrep_rs-0.3.15.dist-info/licenses/LICENSE
ripgrep_rs-0.3.15.dist-info/RECORD
