Metadata-Version: 2.4
Name: ripgrep-rs
Version: 0.3.15
Classifier: Development Status :: 4 - Beta
Classifier: Intended Audience :: Developers
Classifier: License :: OSI Approved :: MIT License
Classifier: Programming Language :: Python :: 3
Classifier: Programming Language :: Python :: 3.12
Classifier: Programming Language :: Python :: 3.13
Classifier: Programming Language :: Python :: 3.14
Classifier: Programming Language :: Rust
Classifier: Topic :: Software Development :: Libraries :: Python Modules
Classifier: Topic :: Text Processing
Requires-Dist: pytest>=8.0 ; extra == 'dev'
Provides-Extra: dev
License-File: LICENSE
Summary: A Python wrapper for ripgrep
Keywords: grep,regex,rg,ripgrep,rust,search
Author-email: Josh Learn <josh@exponent.run>, Indent <noreply@indent.com>
Requires-Python: >=3.12
Project-URL: Homepage, https://github.com/phil65/python-ripgrep
Project-URL: Issues, https://github.com/phil65/python-ripgrep/issues
Project-URL: Repository, https://github.com/phil65/python-ripgrep
